ezbill_pg-0.3.0.dist-info/licenses/LICENSE
your_package/__init__.py
your_package/payment_gateway.py
ezbill_pg-0.3.0.dist-info/METADATA
ezbill_pg-0.3.0.dist-info/WHEEL
ezbill_pg-0.3.0.dist-info/top_level.txt
ezbill_pg-0.3.0.dist-info/RECORD
