Metadata-Version: 2.4
Name: ezbill_pg
Version: 0.3.0
Summary: A small Python package that says hello.
Home-page: https://github.com/yourusername/your-repo
Author: Your Name
Author-email: Your Name <your.email@example.com>
License: MIT
Classifier: Programming Language :: Python :: 3
Classifier: License :: OSI Approved :: MIT License
Classifier: Operating System :: OS Independent
Requires-Python: >=3.7
License-File: LICENSE
Dynamic: author
Dynamic: home-page
Dynamic: license-file
Dynamic: requires-python
